win_automation/__init__.py
win_automation/core.py
win_automation_gui-1.0.0.dist-info/LICENSE
win_automation_gui-1.0.0.dist-info/METADATA
win_automation_gui-1.0.0.dist-info/WHEEL
win_automation_gui-1.0.0.dist-info/top_level.txt
win_automation_gui-1.0.0.dist-info/RECORD
